MANIFEST.in
README
setup.py
MyPackage_379.egg-info/PKG-INFO
MyPackage_379.egg-info/SOURCES.txt
MyPackage_379.egg-info/dependency_links.txt
MyPackage_379.egg-info/top_level.txt
Package1/__init__.py