Metadata-Version: 2.1
Name: MyPackage-379
Version: 0.0.0
Summary: This is my Package
Home-page: UNKNOWN
Author: Me
License: UNKNOWN
Platform: UNKNOWN
